proJSON/__init__.py
proJSON-1.2.7.dist-info/LICENSE
proJSON-1.2.7.dist-info/METADATA
proJSON-1.2.7.dist-info/WHEEL
proJSON-1.2.7.dist-info/top_level.txt
proJSON-1.2.7.dist-info/RECORD
