Metadata-Version: 2.1
Name: proJSON
Version: 1.2.7
Summary: A python library to compress a dict into a bytearray.
Author-email: JKinc <communications@jkinc.co.uk>
Project-URL: Homepage, https://github.com/The-Geiger-Network-Project/proJSON/tree/main
Project-URL: Bug Tracker, https://github.com/The-Geiger-Network-Project/proJSON/tree/main/issues
Classifier: Programming Language :: Python :: 3
Classifier: License :: OSI Approved :: MIT License
Classifier: Operating System :: OS Independent
Requires-Python: >=3.7
License-File: LICENSE
Requires-Dist: lz4 (==4.3.2)
